cryptography/__init__.py
cryptography/ecdsa.py
cryptography/ellipticCurves.py
cryptography/hashing.py
cryptography/rfc6979.py
cryptography/secp256k1.py
cryptography/vectorsForTesting.py
foss_cryptography-2.0.3.dist-info/LICENSE
foss_cryptography-2.0.3.dist-info/METADATA
foss_cryptography-2.0.3.dist-info/WHEEL
foss_cryptography-2.0.3.dist-info/top_level.txt
foss_cryptography-2.0.3.dist-info/RECORD
