Metadata-Version: 2.1
Name: foss_cryptography
Version: 2.0.3
Summary: Elliptic Cryptography and ECDSA
Home-page: https://github.com/stefanogaspari/foss_cryptography
Author: Stefano Gaspari
License-File: LICENSE
